ansible_doc_extractor/__init__.py
ansible_doc_extractor/cli.py
ansible_doc_extractor/templates/module.md.j2
ansible_doc_extractor/templates/module.rst.j2
ansible_doc_extractor-0.1.11.dist-info/LICENSE
ansible_doc_extractor-0.1.11.dist-info/METADATA
ansible_doc_extractor-0.1.11.dist-info/WHEEL
ansible_doc_extractor-0.1.11.dist-info/entry_points.txt
ansible_doc_extractor-0.1.11.dist-info/top_level.txt
ansible_doc_extractor-0.1.11.dist-info/zip-safe
ansible_doc_extractor-0.1.11.dist-info/RECORD
