Metadata-Version: 2.1
Name: ansible-doc-extractor
Version: 0.1.11
Summary: Extract Ansible module documentation
Home-page: https://github.com/xlab-steampunk/ansible-doc-extractor
Author: XLAB Steampunk
Author-email: steampunk@xlab.si
Project-URL: Bug Tracker, https://github.com/xlab-steampunk/ansible-doc-extractor/issues
Keywords: ansible,documentation
Classifier: Development Status :: 2 - Pre-Alpha
Classifier: Environment :: Console
Classifier: Intended Audience :: Developers
Classifier: License :: OSI Approved :: GNU Lesser General Public License v3 or later (LGPLv3+)
Classifier: Programming Language :: Python
Classifier: Programming Language :: Python :: 3
Classifier: Programming Language :: Python :: 3.6
Classifier: Programming Language :: Python :: 3.7
Classifier: Programming Language :: Python :: 3.8
Classifier: Programming Language :: Python :: 3.9
Classifier: Programming Language :: Python :: 3.10
Classifier: Programming Language :: Python :: 3.11
Classifier: Programming Language :: Python :: 3.12
Requires-Python: >=3.6
License-File: LICENSE
Requires-Dist: jinja2
Requires-Dist: PyYAML
Requires-Dist: antsibull-docs-parser <2.0.0,>=1.0.0
Provides-Extra: ansible
Requires-Dist: ansible ; extra == 'ansible'
Provides-Extra: base
Requires-Dist: ansible-base ; extra == 'base'
Provides-Extra: core
Requires-Dist: ansible-core ; extra == 'core'
